[
    {
        "key": "012000",
        "name": "个险首年标准保费"
    },
    {
        "key": "011001",
        "name": "个险首年期交"
    },
    {
        "key": "011010",
        "name": "个险十年期交"
    },
    {
        "key": "011005",
        "name": "个险五年期交"
    },
    {
        "key": "011003",
        "name": "个险三年期交"
    },
    {
        "key": "014000",
        "name": "个险短险保费"
    },     
    {
        "key": "015000",
        "name": "个险每日录单"
    },   
    {
        "key": "015100",
        "name": "个险每日生效"
    },         
    {
        "key": "034000",
        "name": "团险短险保费"
    },
    {
        "key": "035000",
        "name": "团险每日录单"
    },   
    {
        "key": "035100",
        "name": "团险每日生效"
    },
    {
        "key": "022000",
        "name": "银保首年标准保费"
    },
    {
        "key": "021001",
        "name": "银保首年期交"
    },
    {
        "key": "021010",
        "name": "银保十年期交"
    },
    {
        "key": "021005",
        "name": "银保五年期交"
    },
    {
        "key": "021003",
        "name": "银保三年期交"
    },
    {
        "key": "024000",
        "name": "银保短险保费"
    },
    {
        "key": "025000",
        "name": "银保每日录单"
    },  
    {
        "key": "025100",
        "name": "银保每日生效"
    },          
    {
        "key": "002000",
        "name": "全渠道首年标准保费"
    },
    {
        "key": "001001",
        "name": "全渠道首年期交"
    },
    {
        "key": "001010",
        "name": "全渠道十年期交"
    },
   {
        "key": "001005",
        "name": "全渠道五年期交"
    },
    {
        "key": "001003",
        "name": "全渠道三年期交"
    },
    {
        "key": "004000",
        "name": "全渠道短险保费"
    },       
    {
        "key": "005000",
        "name": "全渠道每日录单"
    },
   {
        "key": "005100",
        "name": "全渠道每日生效保费"
    },         
    {
        "key": "042000",
        "name": "电销首年标准保费"
    },
    {
        "key": "041001",
        "name": "电销首年期交"
    },
    {
        "key": "044000",
        "name": "电销短险保费"
    },
    {
        "key": "000000",
        "name": "全渠道保费指标"
    },
    {
        "key": "100000",
        "name": "全渠道人力指标"
    },
    {
        "key": "111000",
        "name": "个险持证人力"
    },
    {
        "key": "112000",
        "name": "收展持证人力"
    },
    {
        "key": "111100",
        "name": "个险季度有效人力"
    },
    {
        "key": "110000",
        "name": "个险销售队伍综合目标达成率"
    },
    {
        "key": "121000",
        "name": "银保保险规划师队人力发展目标"
    },
    {
        "key": "810000",
        "name": "趸交保费预算完成率"
    },
    {
        "key": "810100",
        "name": "保障型业务(10年期及以上)预算完成率"
    },
    {
        "key": "810200",
        "name": "政策性医疗保险业务"
    },
    {
        "key": "810300",
        "name": "费用预算控制率"
    },
    {
        "key": "810400",
        "name": "退保率"
    },
    {
        "key": "810500",
        "name": "死亡重疾给付控制率"
    },
    {
        "key": "810600",
        "name": "风险管控达标率及合规考核达标率"
    },
    {
        "key": "810700",
        "name": "客户服务品质完成率"
    },
    {
        "key": "810800",
        "name": "35家大中城市分公司个险首年期交对标比值变动率"
    },
    {
        "key": "910000",
        "name": "省级分公司个险首年期交对标比值变动率"
    },
    {
        "key": "910100",
        "name": "省级分公司个险月均销售人力对标比值变动率"
    },
    {
        "key": "210000",
        "name": "综合销售和电网销业务预算完成率"
    },
    {
        "key": "210100",
        "name": "长险新客户增长率"
    },
    {
        "key": "210200",
        "name": "保费持续率"
    },
    {
        "key": "999999",
        "name": "经营指标综合得分"
    }
]